curl_to_context-3.2.7.dist-info/METADATA
curl_to_context-3.2.7.dist-info/WHEEL
curl_to_context-3.2.7.dist-info/entry_points.txt
curl_to_context-3.2.7.dist-info/licenses/LICENSE
curl_to_context/__init__.py
curl_to_context/lib/__init__.py
curl_to_context/lib/context.py
curl_to_context/lib/curl_parser.py
curl_to_context/lib/dogman.py
curl_to_context/lib/grab.py
curl_to_context/main.py
curl_to_context/test/__init__.py
curl_to_context/test/test_context.py
curl_to_context/test/test_curl_parser.py
curl_to_context/test/test_dogman.py
curl_to_context/test/test_grab.py
curl_to_context/test/test_main.py
curl_to_context-3.2.7.dist-info/RECORD
