Metadata-Version: 2.1
Name: curl-to-context
Version: 3.2.7
Summary: Convert curl commands to Python code for Grab/Context frameworks
Author-Email: tadeasf <business@tadeasfort.com>
License: GPL-3.0-or-later
Classifier: Development Status :: 5 - Production/Stable
Classifier: Environment :: Console
Classifier: Intended Audience :: Developers
Classifier: License :: OSI Approved :: GNU General Public License v3 or later (GPLv3+)
Classifier: Operating System :: OS Independent
Classifier: Programming Language :: Python :: 3
Classifier: Programming Language :: Python :: 3.10
Classifier: Programming Language :: Python :: 3.11
Classifier: Programming Language :: Python :: 3.12
Classifier: Programming Language :: Python :: 3.13
Project-URL: Homepage, https://github.com/tadeasf/curl-to-context
Project-URL: Repository, https://github.com/tadeasf/curl-to-context
Requires-Python: >=3.10.11
Requires-Dist: pyperclip>=1.9.0
Requires-Dist: typer>=0.15.1
Requires-Dist: rich>=13.9.4
Requires-Dist: six>=1.17.0
Requires-Dist: prompt-toolkit>=3.0.50
Requires-Dist: catppuccin[pygments]>=2.3.4
Requires-Dist: pygments>=2.19.1
